kube_shell-0.0.21.dist-info/DESCRIPTION.rst
kube_shell-0.0.21.dist-info/METADATA
kube_shell-0.0.21.dist-info/RECORD
kube_shell-0.0.21.dist-info/WHEEL
kube_shell-0.0.21.dist-info/entry_points.txt
kube_shell-0.0.21.dist-info/metadata.json
kube_shell-0.0.21.dist-info/top_level.txt
kubeshell/__init__.py
kubeshell/client.py
kubeshell/completer.py
kubeshell/kubeshell.py
kubeshell/lexer.py
kubeshell/logger.py
kubeshell/main.py
kubeshell/style.py
kubeshell/toolbar.py
kubeshell/data/cli.json
