Metadata-Version: 2.0
Name: kube-shell
Version: 0.0.21
Summary: Kubernetes shell: An integrated shell for working with the Kubernetes CLI
Home-page: https://github.com/cloudnativelabs/kube-shell
Author: Cloudnative Labs
Author-email: UNKNOWN
License: Apache License 2.0
Keywords: kubernetes,autocomplete,shell
Platform: UNKNOWN
Classifier: Development Status :: 3 - Alpha
Classifier: Intended Audience :: Developers
Classifier: Intended Audience :: System Administrators
Classifier: Natural Language :: English
Classifier: License :: OSI Approved :: Apache Software License
Classifier: Programming Language :: Python
Classifier: Programming Language :: Python :: 2.7
Classifier: Programming Language :: Python :: 3
Classifier: Programming Language :: Python :: 3.3
Classifier: Programming Language :: Python :: 3.4
Classifier: Programming Language :: Python :: 3.5
Classifier: Programming Language :: Python :: 3.6
Requires-Dist: Pygments (>=2.1.3,<3.0.0)
Requires-Dist: click (>=4.0,<7.0)
Requires-Dist: fuzzyfinder (>=1.0.0)
Requires-Dist: kubernetes (>=0.10.0,<3.0.0)
Requires-Dist: prompt-toolkit (<1.1.0,>=1.0.10)
